Workbook

Sheet Summary
A1: Cash-Flow Summary
A3: Applicant | B3: Rohit Verma
A4: Application ID | B4: APP-009
A5: Employment type | B5: salaried
A6: Net monthly income (income sheet) | B6: 95000
A7: Existing EMIs (avg/month) | B7: =AVERAGE('Monthly Trend'!G2:G7)
A8: Proposed EMI | B8: 11962.17
A9: FOIR | B9: =(B7+B8)/B6
A10: Credit score | B10: 745
A11: Average bank balance | B11: =AVERAGE('Monthly Trend'!H2:H7)
A12: Payment returns | B12: 0
A13: Salary credit months (of 6) | B13: 4
A14: Vintage (months) | B14: 3
A15: Unexplained large cash deposit | B15: No
A17: Decision | B17: REFER
A19: Reasons
A20: R4_VINTAGE | B20: Vintage of 3 months is below the refer threshold of 6 months.

Sheet Transactions
A1: Date | B1: Description | C1: Debit | D1: Credit | E1: Balance | F1: Category
A2: 45845 | B2: ACH Debit - EXISTING LOAN EMI | C2: 4000 | E2: 12074 | F2: emi
A3: 45853 | B3: UPI - UTILITIES & BILLS | C3: 1431 | E3: 10643 | F3: other
A4: 45863 | B4: POS / UPI - HOUSEHOLD SPENDS | C4: 4623 | E4: 6020 | F4: other
A5: 45874 | B5: Salary Credit - EMP PAYROLL | D5: 95000 | E5: 101020 | F5: salary
A6: 45876 | B6: ACH Debit - EXISTING LOAN EMI | C6: 4000 | E6: 97020 | F6: emi
A7: 45884 | B7: UPI - UTILITIES & BILLS | C7: 2550 | E7: 94470 | F7: other
A8: 45894 | B8: POS / UPI - HOUSEHOLD SPENDS | C8: 79948 | E8: 14522 | F8: other
A9: 45905 | B9: Salary Credit - EMP PAYROLL | D9: 95000 | E9: 109522 | F9: salary
A10: 45907 | B10: ACH Debit - EXISTING LOAN EMI | C10: 4000 | E10: 105522 | F10: emi
A11: 45915 | B11: UPI - UTILITIES & BILLS | C11: 2257 | E11: 103265 | F11: other
A12: 45925 | B12: POS / UPI - HOUSEHOLD SPENDS | C12: 81914 | E12: 21351 | F12: other
A13: 45935 | B13: Salary Credit - EMP PAYROLL | D13: 95000 | E13: 116351 | F13: salary
A14: 45937 | B14: ACH Debit - EXISTING LOAN EMI | C14: 4000 | E14: 112351 | F14: emi
A15: 45945 | B15: UPI - UTILITIES & BILLS | C15: 2198 | E15: 110153 | F15: other
A16: 45955 | B16: POS / UPI - HOUSEHOLD SPENDS | C16: 84009 | E16: 26144 | F16: other
A17: 45968 | B17: ACH Debit - EXISTING LOAN EMI | C17: 4000 | E17: 22144 | F17: emi
A18: 45976 | B18: UPI - UTILITIES & BILLS | C18: 2140 | E18: 20004 | F18: other
A19: 45986 | B19: POS / UPI - HOUSEHOLD SPENDS | C19: 5649 | E19: 14355 | F19: other
A20: 45996 | B20: Salary Credit - EMP PAYROLL | D20: 95000 | E20: 109355 | F20: salary
A21: 45998 | B21: ACH Debit - EXISTING LOAN EMI | C21: 4000 | E21: 105355 | F21: emi
A22: 46006 | B22: UPI - UTILITIES & BILLS | C22: 1832 | E22: 103523 | F22: other
A23: 46016 | B23: POS / UPI - HOUSEHOLD SPENDS | C23: 85433 | E23: 18090 | F23: other

Sheet Monthly Trend
A1: Month | B1: Month Start | C1: Month End | D1: Total Credits | E1: Total Debits | F1: Salary Credits | G1: EMI Debits | H1: Month-End Balance
A2: Jul 2025 | B2: 45839 | C2: 45869 | D2: =SUMIFS(Transactions!D2:D23,Transactions!A2:A23,">="&B2,Transactions!A2:A23,"<="&C2) | E2: =SUMIFS(Transactions!C2:C23,Transactions!A2:A23,">="&B2,Transactions!A2:A23,"<="&C2) | F2: =SUMIFS(Transactions!D2:D23,Transactions!A2:A23,">="&B2,Transactions!A2:A23,"<="&C2,Transactions!F2:F23,"salary") | G2: =SUMIFS(Transactions!C2:C23,Transactions!A2:A23,">="&B2,Transactions!A2:A23,"<="&C2,Transactions!F2:F23,"emi") | H2: =INDEX(Transactions!E2:E23,MATCH(MAXIFS(Transactions!A2:A23,Transactions!A2:A23,">="&B2,Transactions!A2:A23,"<="&C2),Transactions!A2:A23,0))
A3: Aug 2025 | B3: 45870 | C3: 45900 | D3: =SUMIFS(Transactions!D2:D23,Transactions!A2:A23,">="&B3,Transactions!A2:A23,"<="&C3) | E3: =SUMIFS(Transactions!C2:C23,Transactions!A2:A23,">="&B3,Transactions!A2:A23,"<="&C3) | F3: =SUMIFS(Transactions!D2:D23,Transactions!A2:A23,">="&B3,Transactions!A2:A23,"<="&C3,Transactions!F2:F23,"salary") | G3: =SUMIFS(Transactions!C2:C23,Transactions!A2:A23,">="&B3,Transactions!A2:A23,"<="&C3,Transactions!F2:F23,"emi") | H3: =INDEX(Transactions!E2:E23,MATCH(MAXIFS(Transactions!A2:A23,Transactions!A2:A23,">="&B3,Transactions!A2:A23,"<="&C3),Transactions!A2:A23,0))
A4: Sep 2025 | B4: 45901 | C4: 45930 | D4: =SUMIFS(Transactions!D2:D23,Transactions!A2:A23,">="&B4,Transactions!A2:A23,"<="&C4) | E4: =SUMIFS(Transactions!C2:C23,Transactions!A2:A23,">="&B4,Transactions!A2:A23,"<="&C4) | F4: =SUMIFS(Transactions!D2:D23,Transactions!A2:A23,">="&B4,Transactions!A2:A23,"<="&C4,Transactions!F2:F23,"salary") | G4: =SUMIFS(Transactions!C2:C23,Transactions!A2:A23,">="&B4,Transactions!A2:A23,"<="&C4,Transactions!F2:F23,"emi") | H4: =INDEX(Transactions!E2:E23,MATCH(MAXIFS(Transactions!A2:A23,Transactions!A2:A23,">="&B4,Transactions!A2:A23,"<="&C4),Transactions!A2:A23,0))
A5: Oct 2025 | B5: 45931 | C5: 45961 | D5: =SUMIFS(Transactions!D2:D23,Transactions!A2:A23,">="&B5,Transactions!A2:A23,"<="&C5) | E5: =SUMIFS(Transactions!C2:C23,Transactions!A2:A23,">="&B5,Transactions!A2:A23,"<="&C5) | F5: =SUMIFS(Transactions!D2:D23,Transactions!A2:A23,">="&B5,Transactions!A2:A23,"<="&C5,Transactions!F2:F23,"salary") | G5: =SUMIFS(Transactions!C2:C23,Transactions!A2:A23,">="&B5,Transactions!A2:A23,"<="&C5,Transactions!F2:F23,"emi") | H5: =INDEX(Transactions!E2:E23,MATCH(MAXIFS(Transactions!A2:A23,Transactions!A2:A23,">="&B5,Transactions!A2:A23,"<="&C5),Transactions!A2:A23,0))
A6: Nov 2025 | B6: 45962 | C6: 45991 | D6: =SUMIFS(Transactions!D2:D23,Transactions!A2:A23,">="&B6,Transactions!A2:A23,"<="&C6) | E6: =SUMIFS(Transactions!C2:C23,Transactions!A2:A23,">="&B6,Transactions!A2:A23,"<="&C6) | F6: =SUMIFS(Transactions!D2:D23,Transactions!A2:A23,">="&B6,Transactions!A2:A23,"<="&C6,Transactions!F2:F23,"salary") | G6: =SUMIFS(Transactions!C2:C23,Transactions!A2:A23,">="&B6,Transactions!A2:A23,"<="&C6,Transactions!F2:F23,"emi") | H6: =INDEX(Transactions!E2:E23,MATCH(MAXIFS(Transactions!A2:A23,Transactions!A2:A23,">="&B6,Transactions!A2:A23,"<="&C6),Transactions!A2:A23,0))
A7: Dec 2025 | B7: 45992 | C7: 46022 | D7: =SUMIFS(Transactions!D2:D23,Transactions!A2:A23,">="&B7,Transactions!A2:A23,"<="&C7) | E7: =SUMIFS(Transactions!C2:C23,Transactions!A2:A23,">="&B7,Transactions!A2:A23,"<="&C7) | F7: =SUMIFS(Transactions!D2:D23,Transactions!A2:A23,">="&B7,Transactions!A2:A23,"<="&C7,Transactions!F2:F23,"salary") | G7: =SUMIFS(Transactions!C2:C23,Transactions!A2:A23,">="&B7,Transactions!A2:A23,"<="&C7,Transactions!F2:F23,"emi") | H7: =INDEX(Transactions!E2:E23,MATCH(MAXIFS(Transactions!A2:A23,Transactions!A2:A23,">="&B7,Transactions!A2:A23,"<="&C7),Transactions!A2:A23,0))
